[
  {
    "name": "강다영",
    "source": "ticket_call",
    "phone": "010-****-5678",
    "type": "자연유입",
    "product": "인터넷/TV",
    "agent": "미배정",
    "status": "신규유입",
    "time": "14:28 (4분)"
  },
  {
    "name": "오서연",
    "source": "ticket_call",
    "phone": "010-****-3312",
    "type": "자연유입",
    "product": "인터넷/TV",
    "agent": "미배정",
    "status": "신규유입",
    "time": "14:31 (1분)"
  },
  {
    "name": "류승현",
    "source": "callback",
    "phone": "010-****-1122",
    "type": "자연유입",
    "product": "유심",
    "agent": "미배정",
    "status": "신규유입",
    "time": "14:35 (방금)"
  },
  {
    "name": "한지민",
    "source": "kakao_chat",
    "phone": "010-****-4433",
    "type": "자연유입",
    "product": "렌탈",
    "agent": "미배정",
    "status": "신규유입",
    "time": "14:22 (10분)"
  },
  {
    "name": "송예진",
    "source": "qna_board",
    "phone": "010-****-5544",
    "type": "자연유입",
    "product": "가전",
    "agent": "미배정",
    "status": "신규유입",
    "time": "14:18 (14분)"
  },
  {
    "name": "최수진",
    "source": "ticket_call",
    "phone": "010-****-8834",
    "type": "자연유입",
    "product": "유심",
    "agent": "이상담",
    "status": "진행중",
    "time": "14:15 (17분)"
  },
  {
    "name": "윤재혁",
    "source": "callback",
    "phone": "010-****-6655",
    "type": "자연유입",
    "product": "인터넷/TV",
    "agent": "김상담",
    "status": "진행중",
    "time": "13:50 (42분)"
  },
  {
    "name": "임수빈",
    "source": "kakao_chat",
    "phone": "010-****-7766",
    "type": "자연유입",
    "product": "렌탈",
    "agent": "박상담",
    "status": "진행중",
    "time": "13:40 (52분)"
  },
  {
    "name": "조민서",
    "source": "callback",
    "phone": "010-****-8877",
    "type": "자연유입",
    "product": "유심",
    "agent": "최상담",
    "status": "진행중",
    "time": "13:20 (72분)"
  },
  {
    "name": "신동훈",
    "source": "ticket_call",
    "phone": "010-****-9988",
    "type": "자연유입",
    "product": "인터넷/TV",
    "agent": "이상담",
    "status": "진행중",
    "time": "13:05 (87분)"
  },
  {
    "name": "권아영",
    "source": "ticket_call",
    "phone": "010-****-1010",
    "type": "자연유입",
    "product": "인터넷/TV",
    "agent": "김상담",
    "status": "설치완료",
    "time": "어제"
  },
  {
    "name": "황선우",
    "source": "kakao_chat",
    "phone": "010-****-2020",
    "type": "자연유입",
    "product": "렌탈",
    "agent": "박상담",
    "status": "설치완료",
    "time": "어제"
  },
  {
    "name": "박지훈",
    "source": "qna_board",
    "phone": "010-****-3030",
    "type": "자연유입",
    "product": "가전",
    "agent": "최상담",
    "status": "설치완료",
    "time": "어제"
  },
  {
    "name": "이채원",
    "source": "callback",
    "phone": "010-****-4040",
    "type": "자연유입",
    "product": "유심",
    "agent": "이상담",
    "status": "설치완료",
    "time": "그제"
  },
  {
    "name": "김성민",
    "source": "ticket_call",
    "phone": "010-****-5050",
    "type": "자연유입",
    "product": "인터넷/TV",
    "agent": "김상담",
    "status": "설치완료",
    "time": "그제"
  },
  {
    "name": "박민준",
    "source": "store",
    "phone": "010-****-2341",
    "type": "DB고객",
    "product": "렌탈",
    "agent": "김상담",
    "status": "업셀링관심있음",
    "time": "D+1",
    "store": "상무점"
  },
  {
    "name": "강나연",
    "source": "store",
    "phone": "010-****-9901",
    "type": "DB고객",
    "product": "유심",
    "agent": "김상담",
    "status": "업셀링관심있음",
    "time": "D+1",
    "store": "동구점"
  },
  {
    "name": "최예나",
    "source": "store",
    "phone": "010-****-6060",
    "type": "DB고객",
    "product": "인터넷/TV",
    "agent": "이상담",
    "status": "업셀링관심있음",
    "time": "D+1",
    "store": "서구점"
  },
  {
    "name": "정우혁",
    "source": "store",
    "phone": "010-****-7070",
    "type": "DB고객",
    "product": "렌탈",
    "agent": "박상담",
    "status": "해피콜대기",
    "time": "D+1",
    "store": "북구점"
  },
  {
    "name": "오지수",
    "source": "store",
    "phone": "010-****-8080",
    "type": "DB고객",
    "product": "가전",
    "agent": "최상담",
    "status": "해피콜대기",
    "time": "D+2 ⚠",
    "store": "남구점"
  },
  {
    "name": "강민준",
    "source": "store",
    "phone": "010-****-9090",
    "type": "DB고객",
    "product": "인터넷/TV",
    "agent": "김상담",
    "status": "해피콜대기",
    "time": "D+2 ⚠",
    "store": "광산점"
  },
  {
    "name": "류하은",
    "source": "store",
    "phone": "010-****-1111",
    "type": "DB고객",
    "product": "유심",
    "agent": "이상담",
    "status": "해피콜대기",
    "time": "D+2 ⚠",
    "store": "목포점"
  },
  {
    "name": "한승준",
    "source": "store",
    "phone": "010-****-2222",
    "type": "DB고객",
    "product": "렌탈",
    "agent": "박상담",
    "status": "해피콜대기",
    "time": "D+1",
    "store": "여수점"
  },
  {
    "name": "송지아",
    "source": "store",
    "phone": "010-****-3333",
    "type": "DB고객",
    "product": "인터넷/TV",
    "agent": "최상담",
    "status": "해피콜대기",
    "time": "D+1",
    "store": "순천점"
  },
  {
    "name": "윤미래",
    "source": "store",
    "phone": "010-****-4444",
    "type": "DB고객",
    "product": "가전",
    "agent": "김상담",
    "status": "해피콜대기",
    "time": "D+1",
    "store": "나주점"
  },
  {
    "name": "임도현",
    "source": "store",
    "phone": "010-****-5555",
    "type": "DB고객",
    "product": "인터넷/TV",
    "agent": "이상담",
    "status": "해피콜대기",
    "time": "D+1",
    "store": "강남점"
  },
  {
    "name": "조서윤",
    "source": "store",
    "phone": "010-****-6666",
    "type": "DB고객",
    "product": "렌탈",
    "agent": "박상담",
    "status": "해피콜대기",
    "time": "D+1",
    "store": "마포점"
  },
  {
    "name": "정다은",
    "source": "store",
    "phone": "010-****-4421",
    "type": "DB고객",
    "product": "인터넷/TV",
    "agent": "박상담",
    "status": "계약완료",
    "time": "어제",
    "store": "종로점"
  },
  {
    "name": "신예린",
    "source": "store",
    "phone": "010-****-7777",
    "type": "DB고객",
    "product": "유심",
    "agent": "최상담",
    "status": "계약완료",
    "time": "어제",
    "store": "서초점"
  },
  {
    "name": "권태양",
    "source": "store",
    "phone": "010-****-8888",
    "type": "DB고객",
    "product": "렌탈",
    "agent": "김상담",
    "status": "계약완료",
    "time": "어제",
    "store": "송파점"
  },
  {
    "name": "황지혜",
    "source": "store",
    "phone": "010-****-9999",
    "type": "DB고객",
    "product": "인터넷/TV",
    "agent": "이상담",
    "status": "계약완료",
    "time": "어제",
    "store": "영등포점"
  },
  {
    "name": "박준혁",
    "source": "store",
    "phone": "010-****-1001",
    "type": "DB고객",
    "product": "가전",
    "agent": "박상담",
    "status": "계약완료",
    "time": "그제",
    "store": "성북점"
  },
  {
    "name": "이소율",
    "source": "store",
    "phone": "010-****-2002",
    "type": "DB고객",
    "product": "인터넷/TV",
    "agent": "최상담",
    "status": "계약완료",
    "time": "그제",
    "store": "상무점"
  },
  {
    "name": "김민채",
    "source": "store",
    "phone": "010-****-3003",
    "type": "DB고객",
    "product": "렌탈",
    "agent": "김상담",
    "status": "계약완료",
    "time": "그제",
    "store": "동구점"
  },
  {
    "name": "최현우",
    "source": "store",
    "phone": "010-****-4004",
    "type": "DB고객",
    "product": "유심",
    "agent": "이상담",
    "status": "계약완료",
    "time": "3일전",
    "store": "서구점"
  },
  {
    "name": "정수아",
    "source": "store",
    "phone": "010-****-5005",
    "type": "DB고객",
    "product": "인터넷/TV",
    "agent": "박상담",
    "status": "계약완료",
    "time": "3일전",
    "store": "북구점"
  },
  {
    "name": "오재현",
    "source": "store",
    "phone": "010-****-6006",
    "type": "DB고객",
    "product": "가전",
    "agent": "최상담",
    "status": "계약완료",
    "time": "3일전",
    "store": "남구점"
  },
  {
    "name": "김태호",
    "source": "store",
    "phone": "010-****-7755",
    "type": "DB고객",
    "product": "가전",
    "agent": "최상담",
    "status": "재연락예약",
    "time": "오늘 16:00",
    "store": "광산점"
  },
  {
    "name": "강서윤",
    "source": "store",
    "phone": "010-****-7007",
    "type": "DB고객",
    "product": "인터넷/TV",
    "agent": "김상담",
    "status": "재연락예약",
    "time": "오늘 17:00",
    "store": "목포점"
  },
  {
    "name": "류민호",
    "source": "store",
    "phone": "010-****-8008",
    "type": "DB고객",
    "product": "렌탈",
    "agent": "이상담",
    "status": "재연락예약",
    "time": "내일 10:00",
    "store": "여수점"
  },
  {
    "name": "한채연",
    "source": "store",
    "phone": "010-****-9009",
    "type": "DB고객",
    "product": "유심",
    "agent": "박상담",
    "status": "재연락예약",
    "time": "내일 14:00",
    "store": "순천점"
  },
  {
    "name": "송현준",
    "source": "store",
    "phone": "010-****-1100",
    "type": "DB고객",
    "product": "인터넷/TV",
    "agent": "최상담",
    "status": "재연락예약",
    "time": "내일 15:00",
    "store": "나주점"
  },
  {
    "name": "윤지수",
    "source": "store",
    "phone": "010-****-2200",
    "type": "DB고객",
    "product": "렌탈",
    "agent": "김상담",
    "status": "재연락예약",
    "time": "모레 10:00",
    "store": "강남점"
  },
  {
    "name": "임세아",
    "source": "store",
    "phone": "010-****-3300",
    "type": "DB고객",
    "product": "인터넷/TV",
    "agent": "이상담",
    "status": "미처리",
    "time": "03.15",
    "store": "마포점"
  },
  {
    "name": "조태희",
    "source": "store",
    "phone": "010-****-4400",
    "type": "DB고객",
    "product": "인터넷/TV",
    "agent": "박상담",
    "status": "미처리",
    "time": "03.15",
    "store": "종로점"
  },
  {
    "name": "신현민",
    "source": "store",
    "phone": "010-****-5500",
    "type": "DB고객",
    "product": "렌탈",
    "agent": "미배정",
    "status": "미처리",
    "time": "03.14",
    "store": "서초점"
  },
  {
    "name": "권수빈",
    "source": "store",
    "phone": "010-****-6600",
    "type": "DB고객",
    "product": "인터넷/TV",
    "agent": "미배정",
    "status": "미처리",
    "time": "03.14",
    "store": "송파점"
  },
  {
    "name": "황도연",
    "source": "store",
    "phone": "010-****-7700",
    "type": "DB고객",
    "product": "인터넷/TV",
    "agent": "최상담",
    "status": "진행중",
    "time": "12:30 (잠시후 재개)",
    "store": "영등포점"
  },
  {
    "name": "박서현",
    "source": "store",
    "phone": "010-****-8800",
    "type": "DB고객",
    "product": "렌탈",
    "agent": "김상담",
    "status": "진행중",
    "time": "11:00 (재연결중)",
    "store": "성북점"
  },
  {
    "name": "이준호",
    "source": "store",
    "phone": "010-****-9900",
    "type": "DB고객",
    "product": "유심",
    "agent": "이상담",
    "status": "진행중",
    "time": "10:30 (대기중)",
    "store": "상무점"
  }
]